{
  "web_scraping": {
    "state": "CLOSED",
    "failure_count": 0,
    "success_count": 0,
    "last_state_change": 1743419042.6890619,
    "last_failure_time": 0,
    "last_success_time": 1743419044.03695,
    "total_failures": 0,
    "total_successes": 1,
    "total_requests": 1,
    "failure_timestamps": [],
    "consecutive_failures": 0
  },
  "yahoo_finance": {
    "state": "CLOSED",
    "failure_count": 0,
    "success_count": 0,
    "last_state_change": 1743421576.2671528,
    "last_failure_time": 0,
    "last_success_time": 1743421576.9886458,
    "total_failures": 0,
    "total_successes": 2,
    "total_requests": 2,
    "failure_timestamps": [],
    "consecutive_failures": 0
  }
}